playwright_odoo/__init__.py
playwright_odoo/main.py
playwright_odoo-0.1.dev0.dist-info/LICENSE
playwright_odoo-0.1.dev0.dist-info/METADATA
playwright_odoo-0.1.dev0.dist-info/WHEEL
playwright_odoo-0.1.dev0.dist-info/RECORD
